depgraphviz/main.py
depgraphviz/static/css/styles.css
depgraphviz/static/js/simulate_graph.js
depgraphviz/templates/force_graph.html
depgraphviz/trace_imports.py
depgraphviz-0.1.2.dist-info/entry_points.txt
depgraphviz-0.1.2.dist-info/LICENSE.txt
depgraphviz-0.1.2.dist-info/METADATA
depgraphviz-0.1.2.dist-info/WHEEL
depgraphviz-0.1.2.dist-info/RECORD
